sshmng/__init__.py
sshmng/cli.py
sshmng-0.1.0.dist-info/AUTHORS.rst
sshmng-0.1.0.dist-info/LICENSE
sshmng-0.1.0.dist-info/METADATA
sshmng-0.1.0.dist-info/WHEEL
sshmng-0.1.0.dist-info/entry_points.txt
sshmng-0.1.0.dist-info/top_level.txt
sshmng-0.1.0.dist-info/RECORD
