Metadata-Version: 2.1
Name: sshmng
Version: 0.1.0
Summary: SSH Connection Mangement CLI
Home-page: https://github.com/zeroam/sshmng
Author: Jayone
Author-email: imdff0803@gmail.com
License: MIT license
Keywords: sshmng
Platform: UNKNOWN
Classifier: Development Status :: 2 - Pre-Alpha
Classifier: Intended Audience :: Developers
Classifier: License :: OSI Approved :: MIT License
Classifier: Natural Language :: English
Classifier: Programming Language :: Python :: 3
Classifier: Programming Language :: Python :: 3.5
Classifier: Programming Language :: Python :: 3.6
Classifier: Programming Language :: Python :: 3.7
Classifier: Programming Language :: Python :: 3.8
Requires-Python: >=3.5
Requires-Dist: Click (>=7.0)
